{
  "name": "react-flow-architect",
  "description": "Expert ReactFlow architect for building interactive graph applications with hierarchical node-edge systems, performance optimization, and auto-layout integration. Use when creating or refactoring R...",
  "version": "0.0.34",
  "author": "Sopra Steria Group",
  "license": "UNLICENSED",
  "repository": "https://innersource.soprasteria.com/ssg-ia/ai.backbone/cognitive-hub/internals/ai-sdlc-foundation",
  "tags": [
    "skills",
    "sdlc"
  ],
  "skills": "./"
}
